{"id":"3_9","num":"3.9","title":"MADDE KULLANIM BOZUKLUĞUNA YAKLAŞIM","slug":"madde-kullanim-bozukluguna-yaklasim","category":"koruyucu","depth":2,"pdf_page":979,"preview":"Madde Kullanım Bozukluğuna Yaklaşım  3.9. MADDE KULLANIM BOZUKLUĞUNA YAKLAŞIM Algoritma  BÖLÜM:SEMPTOMLARA KORUYUCU SAĞLIK VE ÖZEL DURUMLARA 1.3.BÖLÜM: VE BULGULARA YAKLAŞIM YAKLAŞIM  Şekil 204. Madde Kullanım Bozukluğuna Yaklaşım Akış  Madde Kullanım Bozukluğuna Yaklaşım  TANIM VE SIKLIK  ◊ Bağımlılık önce deneme ile başlayan, daha sonra daha sık ve riskli kullanımla devam eden bir süreçtir. ◊ Bağımlılıkta tedavi uzun süreli hatta yaşam boyudur, yüksek maliyetlidir ve tedavinin başarısı öngörül","subsections":{"intro":"Madde Kullanım Bozukluğuna Yaklaşım\n\n3.9. MADDE KULLANIM BOZUKLUĞUNA YAKLAŞIM","Algoritma":"BÖLÜM:SEMPTOMLARA\nKORUYUCU SAĞLIK\nVE ÖZEL DURUMLARA\n1.3.BÖLÜM:\nVE BULGULARA\nYAKLAŞIM YAKLAŞIM\n\nŞekil 204. Madde Kullanım Bozukluğuna Yaklaşım Akış\n\nMadde Kullanım Bozukluğuna Yaklaşım\n\nTANIM VE SIKLIK\n\n◊ Bağımlılık önce deneme ile başlayan, daha sonra daha sık ve riskli kullanımla\ndevam eden bir süreçtir.\n◊ Bağımlılıkta tedavi uzun süreli hatta yaşam boyudur, yüksek maliyetlidir ve\ntedavinin başarısı öngörülebilir değildir. Bu yüzden birincil önleme yani insanların\nmadde kullanmaması asıl hedefimizdir.\n◊ İkinci hedef kullanan bireylerin bağımlı olmasını önlemektir. Bu da ikincil\nönleme yani bağımlılık yapıcı maddeyi deneyenlere müdahaleyi kapsar. Deneme\naşamasında olan ergenler ya da yetişkinler psikiyatriye değil birinci basamak\nsağlık hizmetlerine başvurduklarından gerekli müdahale buralarda yapılmalıdır.\n◊ Vücuda alındığında merkezi sinir sistemini etkileyerek fiziksel, ruhsal ve\ndavranışsal değişikliklere sebep olan, bitkisel kimyasal işlemler sonucu oluşturulan\nsentetiklerden elde edilen, sakinleştirici ve/veya uyarıcı etkileri bulunan, kullanma\nisteği durdurulamayan ve kullanılmadığında yoksunluk belirtileri ortaya çıkan tüm\nmaddeler uyuşturucudur.\n◊ Bağımlılık, kronik seyirli bir hastalık olması, bağımlılığa bağlı ortaya çıkan sağlık\nsorunları, bulaşıcı hastalıklara ilişkin risklerin artması, tedavi ve rehabilitasyon\nmaliyetleri, iş gücü kayıpları, uyuşturucu kullanımı olan bireylerde suç işleme, suça\nkarışma, şiddet gibi adli olaylar, aile içi sorunların, ekonomik sorunların artmasvı\nsebebiyle önemli bir toplumsal sorundur.\n◊ Genel Nüfusta Tütün Alkol ve Madde Kullanımına Yönelik Tutum ve Davranış\nAraştırması” verilerine göre 2011 yılında hayatında en az bir kere uyuşturucu madde\nkullananların oranı yüzde 2,7 iken 2018 yılı sonuçlarına göre bu oranın yüzde 3,1’dir.\nTablo 292. MKB tanı kriterleri, DSM 5 (DSM-5, Amerikan Psikiyatri Birliği, Hekimler\nYayın Birliği, 2013’den alınarak düzenlenmiştir).\nAşağıdakilerden en az ikisinin 12 aylık bir süre içinde ortaya çıkmasıyla kendini\ngösteren, klinik olarak önemli bozulmaya yol açan madde kullanımı.\n1. Amaçlanandan daha fazla miktarlarda veya daha uzun süre madde kullanımı\n2 Madde kullanımını azaltmak veya bırakmak istemek ama bunu başaramamak\n3 Maddeye ulaşmak, alkol kullanmak ya da oluşturduğu etkilerden kurtulmak için\nzaman harcaması\n4. Madde kullanmak için güçlü bir dürtü veya istek duymak\n5. İş, ev ya da okulda konumunun gereği olan sorumluluklarını yerine getirememe\nile sonuçlanan madde kullanımı olması\n6. Sosyal yaşamda ya da diğer insanlarla ilişkilerde kalıcı ve tekrarlayıcı sorunlara\nyol açtığı ya da bu sorunları ağırlaştırdığı halde madde kullanımına devam etme\n7. Önemli sosyal, mesleki etkinlikler ve ilgi alanlarına ilişkin etkinliklerin azaltılması\nya da bırakılması\n8. Fiziksel olarak tehlikeli olabilecek durumlarda yineleyici bir şekilde madde\nkullanımının olması\n\nBÖLÜM:SEMPTOMLARA\nKORUYUCU SAĞLIK\nVE ÖZEL DURUMLARA\n1.3.BÖLÜM:\nVE BULGULARA\nYAKLAŞIM YAKLAŞIM\n\n9. Fizyolojik ve psikolojik olarak sıkıntı yaşamasına rağmen kullanmaya devam\netmek\n10. İstenen etkiyi elde etmek için daha fazla madde kullanımı veya aynı ölçüde\nmadde kullanımına karşı daha az etki sağlanması (tolerans)\n11. Kesilme (yoksunluk) belirtileri\nYukarıdaki tanı ölçütlerinden 2 ve üzeri=MKB\nŞiddeti: Hafif: 2-3 semptom, Orta: 4-5 semptom, Şiddetli: ≥6 semptom\n\nDEĞERLENDİRME VE TARAMA\n\n◊ Madde etkisi altında olan hasta ile görüşme yapmayın, ayık olacağı başka\nbir zamana randevu verin. Kendisi ve ailesini başvurabileceği yerler konusunda\nbilgilendirin.\n◊ Madde kullanıp kullanmadığı sorulduğunda EVET yanıtı veren herkese\nkonuştuklarınızın gizli kalacağını vurgulayarak BAPİRT (Bağımlılık Profil İndeksi Risk\nTarama Formu) Madde Ölçeği ile risk taraması yapılmalıdır (Tablo 293)\n◊ BAPİRT Madde taramasını uygularken birden çok madde kullanıyorsa en çok\nkullandığı maddeyi öğrenin. Tüm madde kullanımını toplama yazın.\nTablo 293. BAPİRT Madde Tarama Ölçeği (Kültegin Ögel’in izni ile, Ögel K ve ark.,\nSAMBART Rehberi, Yeniden Yayınları, 2015’den alınmıştır).\nM1 Son bir yıl içinde ne sıklıkta [madde]\nkullandınız?\nM2 [Maddeyi] kestiğinizde veya azalttığınızda\nbazı sorunlar ortaya çıktı mı?\nM3 [Madde] kullandığınız için hayatınızdaki\nbaşka etkinliklerden vazgeçtiğiniz oldu mu?\nM4 [Madde] kullanmak beden veya ruh\nsağlığınızı olumsuz yönde etkiledi mi?\nM5 [Madde] kullanmanız, az sonra sayacağım\nyaşam alanlarından birisi üstünde olumsuz\netkileri oldu mu? Aile ilişkilerinizde?\nArkadaşlarınızla olan ilişkilerinizde? Eğitim\nhayatınızda? İş hayatınızda?\n\nHiçbir zaman\n\nEn az bir kez\n\nÜçten fazla kez\n\nHiçbir zaman\n\nBazen\n\nÇok sık\n\nHiçbir zaman\n\nBazen\n\nÇok sık\n\nHiçbir zaman\n\nBazen\n\nÇok sık\n\nHiçbir zaman\n\nBazen\n\nÇok sık\n\nMadde Kullanım Bozukluğuna Yaklaşım\n\nM6 Gündüz saatlerinde de [madde] kullandığınız Hiçbir zaman\noldu mu?\nBazen\nM7 Hayatınız boyunca hiç damar yoluyla bir\nmadde kullandığınız oldu mu?\n\nÇok sık\n\nHiçbir zaman\n\nBazen\n\nÇok sık\n\nDeğerlendirme: M1-6 puanlarını toplayın.\n4 ve = yüksek riskli\nmadde kullanımı. Damar yolu ile madde kullanımı varsa ölçeği uygulamadan\nyüksek risk kabul edin.\n\nİntoksikasyon\n◊ Madde alımı ya da kısa bir süre sonrasında gelişen ve başka bir nedene bağlı\nolmayan; paranoid hezeyanlar ya da psikotik bir tablo, anksiyete, taşikardi, bulantı,\nepileptik nöbetler, aritmi, serebrovasküler olaylar gibi belirtilerle ortaya çıkan\nintoksikasyon durumunda hasta acil servise sevk edilmelidir.\nMadde Yoksunluğu\n◊ Hastanın yoksunluk belirtileri yaşayıp yaşamadığını değerlendirilmelidir (Tablo\n294).\n◊ Madde kullanıcıları azaltıp, bıraktıkları zaman bazı septomlar ortaya çıkabilir.\nUygulanacak semptoma yönelik tedavi ile hasta biraz rahatlar. Bu sayede hasta\nkontrole gelebilir ve bizimle bağlantısı devam eder. Gerektiğinde sevk etmek için\nde fırsatımız olur.\n◊ Sık görülen uyku sorunları için antihistaminik veya antidepresanlar kullanılabilir\n(mirtazapin, mianserin, trazadon) kullanılabilir.\n◊ Madde kullanan bireyde fiziksel ağrılar, kas spazmları, bulantı ve kusma gibi\nbelirtiler gözlenebilir, bunlara yönelik semptomatik tedavi verilmelidir.\n◊ MKB’a eşlik ruhsal eden ve fiziksel semptomlar araştırılmalı ve gerekirse\nsemptomatik tedavi verilmelidir. Eşlik eden ruhsal sorun aynı anda tedavi\nedilmelidir. Depresyon ve anksiyete hafif düzeyde ise gerekli tedaviler verilmelidir.\n◊ MKB’da gerekli tetkikler yapılmalı ve değerlendirilmelidir.\n\nBÖLÜM:SEMPTOMLARA\nKORUYUCU SAĞLIK\nVE ÖZEL DURUMLARA\n1.3.BÖLÜM:\nVE BULGULARA\nYAKLAŞIM YAKLAŞIM\n\nTablo 294. Maddelerin Yoksunluk Belirtileri\nEsrar ve sentetik kannaboidlerV\n\nOpioidler\n\nBenzodiazepinler\n\nÜşüme,titreme,terleme\nBaş ağrısı,miyalji,somatik ağrılar\nHuzursuzluk, sinirlilik\nÇarpıntı, hipertansiyon\nUykusuzluk\nDürtüsellik\nHafıza bozukluğu\nAnksiyete, irritabilite, ajitasyon\nPsikoz (halüsinasyon ve sanrılar)\nEpileptik nöbetler\n\nTerleme\nBurun akıntısı\nİshal\nUykusuzluk\nSinirlilik\nHuzursuzluk\nAğrı ve kramplar\nŞiddetli madde isteği\nMidriyazis\n\nTerleme, titreme\nKaslarda ağrı, kasılma\nBaş dönmesi, sersemlik\nDiplopi, bulanık görme\nTinnitus, baş ağrısı\nBulantı, kusma, ishal\nParestezi, grip belirtileri\nUykusuzluk,anksiyete,depresyon\nAlgı bozuklukları\nİrritabilite,huzursuzluk,ajitasyon\n\nUyarıcı Maddeler (kokain, ekstazi,\namfetamin, metamfetamin)\n\nİnhalanlar\n\nHalüsinojenler\n\nYoğun aşerme, ajitasyon, irritabilite\nDepresyon, anksiyete\nHayattan keyif alamama\nDurgunluk, yorgunluk\nUyku ve iştah artışı\nKas ağrıları, intihar fikirleri\n\nTerleme,taşikardi\nbulantı,kusma\nUykusuzluk,\nhuzursuzluk, Dikkat,\nkonsantrasyonda\nbozulma, İştah kaybı\nBurun akıntısı, sulu\ngözler, ,\nDepresyon,\nanksiyete\n\nYorgunluk, sinirlilik\nAnhedoni\nAşerme\nDepresif belirtiler\n\nTEDAVİ\n\n◊ Birinci basamak sağlık hizmetlerinde verilen kısa danışmanlığın (5-10 dakika),\nMKB ‘da tedaviye yönlendirmede etkili olduğu bilinmektedir.\n◊ Değişim döngüsü modelinde (Prochaska ve Di Clemente) kişinin hangi evrede\nolduğunu bilerek müdahale yapmak gerekmektedir. Farkındalık öncesinde olan\nbir kişiden maddeyi bırakmasını istemek işe yaramayacaktır. Onun farkındalık\nevresine geçişini sağlamak önemlidir. Farkına varma evresinde ise, kişinin\nmaddeyi bırakmasını istemek yerine madde kullanımını bırakma kararını vermesini\nsağlamaya çalışmalıdır.\n◊ Madde kullananlar bırakmak istemeyebilir, bırakma düşüncesi anksiyete\nyarattığından denemek istemezler ya da istedikleri zaman bırakabileceklerine\ninanırlar. Bu nedenle kişi kesmeyi reddediyorsa, bazen bırakmak yerine kullandığı\nmaddenin miktarını veya kullanım sıklığını azaltmak önerilebilir. Kişi kullandığı\nmaddenin miktarını veya kullanım sıklığını azaltamadığını gördüğünde, bırakmanın\ngerekliliği konusunda daha kolay ikna olur.\n\nMadde Kullanım Bozukluğuna Yaklaşım\n\nTablo 295. Değişim Evreleri\nEvreler\n\nÖzellikleri\n\nHasta söylemleri\n\nFarkındalık Öncesi\n\nAMK olumsuz etkileri farkında\ndeğildirler. Zararı olduğuna\ninanmazlar. Değişime hazır\ndeğildirler.\n\n‘AMK benim için sorun\nyaratmıyor’\n‘Bırakmak/azaltmak\nistemiyorum’\n\nFarkındalık\n\nAMK zararlarının/kendini\nolumsuz etkilediğinin\nfarkındadır. Ama bırakmayı\ndüşünmezler.\n\n‘AMK benim için\nsorun ama bırakmayı\ndüşünmüyorum’\n\nHazırlık\n\nBırakmaya karar vermiş ama\nhenüz eyleme geçmemiştir.\n\n‘Bırakacağım’\n\nEylem\n\nAlkol/maddeyi bırakmıştır.\nTekrar başlama riski yüksektir.\n\n‘Bıraktım’\n\nSürdürme\n\nBırakmayı sürdürme\nçabasındadır.\n\n‘Bir aydır içmiyorum’\n\nYeniden Başlama\n\nTekrar AMK’a başlamıştır.\n\n‘Tekrar içmeye başladım’\n\n◊ Adsız Narkolikler (AN), 12 basamak yaklaşımı uygulayan kendi kendine yardım\ngruplarıdır. Bu sayede madde bağımlılarına duygusal destek sunan bir uluslararası\nkuruluştur. Adsız narkotiklere devam eden bireylerin ayık kalma sürelerinin daha\nuzun olduğu gösterilmiştir. AN’nin etkililiği katılımcılara sağladığı sosyalleşme\nimkânı ve ayık kalma motivasyonu bireye maddeden uzak kalma konusunda\nyardımcı olmaktadır.\n◊ AMATEM, alkol ve madde kullanım bozukluğu konusunda tedavi ve eğitim\namacıyla kurulmuş olup, AMATEM bünyesinde gerçekleştirilen müdahale yöntemi\nüç bölümden oluşur; “Detoksifikasyon (arındırma), ilaçla müdahale ve psikososyal (ilaçsız) müdahale.\n◊ Detoksifikasyon aşamasında madde bağımlısının maddeye olan arzusundan\nkaynaklanan yoksunluk belirtilerinin azaltılması amacıyla uygulanacak olan\nmüdahaleler gerçekleştirilmektedir. Bu aşama 7 ila 10 gün arasında bir zamanda\ntamamlanmaktadır.\n◊ Farmakolojik müdahale aşmasında ise detoksifikasyon süreci sona erince\nbağımlılık tedavisinde kullanılan ilaçların başlanması ile iyileşme süreci devam\netmektedir.\n◊ Son aşama olan psiko-sosyal müdahale sürecinde ise bağımlının alkol veya\nmaddeye tekrardan yönelmemesi için gerekli olan psiko-sosyal faaliyetler\ngerçekleştirilmektedir. Psikoterapiler ve benzeri grup çalışmaları ile yaklaşık olarak\n14 gün ile 28 gün arasındaki bir zaman diliminde süreç tamamlanmaktadır.\n\nBÖLÜM:SEMPTOMLARA\nKORUYUCU SAĞLIK\nVE ÖZEL DURUMLARA\n1.3.BÖLÜM:\nVE BULGULARA\nYAKLAŞIM YAKLAŞIM\n\n‘Benim içmem bir\nazaltmak istemiyorum.’\n\nEYLEM\nHAZIRLIK\n\nFARKINDALIK\n\nAncak bu evrede tekrar\n\nSÜRDÜRME\n\nistemektedir. Ancak\nsürdürmektedir.\nolumsuz etkilerin\n\nFARKINDALIK\n‘Benim içmem bir sorun\n\nMaddenin kendisini\nolumsuz yönde\nAncak henüz madde\n\n‘Tekrar içmeye\n\nDÖNGÜSÜ\n\nTekrar madde\n\nŞekil 205. Değişim Döngüsü\n◊ Ergenlerde risk taraması ergenler için hazırlanmış Madde Anketi kullanılmalıdır\n(Tablo 296).\n◊ Ergenin madde kullanımı yanında ruhsal sorunu olup olmadığı, yoksunluk\nbelirtileri yaşayıp yaşamadığı ve hangi maddeleri kullanıp kullanmadığı öğrenilir.\nEğer eşlik eden ruhsal sorunlar, yoksunluk belirtileri ve birden fazla madde kullanımı\nvarsa, psikiyatriye sevk edilmelidir.\n◊ Aileyle muhakkak görüşülmeli ve aile bilgilendirilmelidir.\n◊ Yüksek riskli kullanımı olan gençler ise bağımlılık merkezlerine yönlendirilmelidir.\nEğer gitmek istemezse değişim motivasyonunu artırmak için görüşme yapılmalı\nve tekrar etkin tavsiyede bulunulmalıdır (Şekil 206. Ergenlerde Alkol/Madde\nKullanımına Yaklaşım Akış Şeması).\nTablo 296. Ergen Madde Risk Tarama Ölçeği (Kültegin Ögel’in izni ile, Ögel K ve\nark., SAMBART Rehberi, Yeniden Yayınları, 2015’den alınmıştır).\nGM1 Son bir yıl içinde ne sıklıkta [madde] kullandın? Hiç\n\nSadece bir iki kez\n\nAyda 1-3 kere\n\nHaftada 1-5 kez\n\nHemen hemen her gün 4\n2 puan ve üstü YÜKSEK RİSKLİ kullanıma işaret etmektedir.\n\nMadde Kullanım Bozukluğuna Yaklaşım\n\nŞekil 206. Ergenlerde Alkol/Madde Kullanımına Yaklaşım Akış Şeması\n\nGüncel Kılavuzlar ve Ek Kaynaklar\n1. SAMBART – Birinci Basamakta Alkol ve Madde Kullanımına Yönelik Kısa Müdahale\nRehberi (Ögel K. ve ark.) https://www.yeniyayinlari.com.tr/sigara-alkol-ve-maddebagimliligi-rehberlik-ve-tarama-programi-sambart [cited 2025 Dec 26].\n2. Alkol ve Madde Kullanım Bozuklukları Tedavi ve İzlem Klinik Protokolü – T.C. Sağlık\nBakanlığı (2022) https://shgm.saglik.gov.tr/TR-98392/alkol-ve-madde-kullanimbozukluklari-tedavi-ve-izlem-klinik-protokolu.html [cited 2025 Dec 26].\n3. WHO – The ASSIST-linked brief intervention for hazardous and harmful\nsubstance use (Primary Care Manual) https://www.who.int/publications/i/item/\nWHO-MSD-MER-10.1 [cited 2025 Dec 26].","Kaynakça":"1. Amerikan Psikiyatri Birliği. (2013). Ruhsal bozuklukların tanısal ve sayımsal el\nkitabı (5. Bs.) içinde (s. 237-239). (Çev. Köroğlu, E.). Ankara: Hekimler Yayın Birliği.\n2. Bağımlılık Tanı ve Tedavi Temel Kitabı N. Dilbaz, I. Göğceğiz, C. O. Noyan, Ö. Kazan\nKızılkurt (eds). Ankara Nobel Tıp Kitabevleri, 237-260. 2022. ISBN; 978-625-7146-77-7\n\nBÖLÜM:SEMPTOMLARA\nKORUYUCU SAĞLIK\nVE ÖZEL DURUMLARA\n1.3.BÖLÜM:\nVE BULGULARA\nYAKLAŞIM YAKLAŞIM\n\n4. Acar, T. (2024). Madde Kullanımı Açısından Koruyucu Hekimlik. Turkiye Klinikleri\nFamily Medicine-Special Topics, 15(2), 83-87\n5. US Preventive Services Task Force. Screening for unhealthy drug use:\nUS Preventive Services Task Force recommendation statement. JAMA.\n2020;323(22):2301–2309.\n6. Şengezer,Tijen (2020).”Madde Kullanım Bozuklukları için Davranışsal Terapiler”.\nEsra Saatçi (Ed.)Rakel Aile Hekimliği Dokuzuncu Baskı(pp.1152-1163).Ankara:Güneş\nTıp Kitabevleri\n7. Kahan M. Management of substance use disorders in primary care. Toronto:\nWomen's College Hospital; 2015.\n8. Kılıç M, Önal S. Birinci basamak sağlık hizmetlerinde alkol-madde kullanımı olan\nbireylere yaklaşım. Turkish Journal of Family Practice. 2023;14(3):390–6. doi:10.15511/\ntjtfp.23.00390.\n9. Şengezer Tijen, Hasan Kaya (2020).”Aile Hekimliğinde Alkol ve Madde Kullanım\nBozuklukları”Aydın Çiftçi(Ed).Birinci Basamakta ve Aile Hekimliğinde Güncel Tanı ve\nTedavi (pp.103-110).Ankara: Nobel Tıp Kitabevleri.\n10. Hooker SA, Punjabi A, Justesen K, Boyle L, Sherman MD. Encouraging health\nbehavior change: eight evidence-based strategies. Fam Pract Manag. 2018\nMar-Apr;25(2):31–36"},"full_text":"Madde Kullanım Bozukluğuna Yaklaşım\n\n3.9. MADDE KULLANIM BOZUKLUĞUNA YAKLAŞIM\nAlgoritma\n\nBÖLÜM:SEMPTOMLARA\nKORUYUCU SAĞLIK\nVE ÖZEL DURUMLARA\n1.3.BÖLÜM:\nVE BULGULARA\nYAKLAŞIM YAKLAŞIM\n\nŞekil 204. Madde Kullanım Bozukluğuna Yaklaşım Akış\n\nMadde Kullanım Bozukluğuna Yaklaşım\n\nTANIM VE SIKLIK\n\n◊ Bağımlılık önce deneme ile başlayan, daha sonra daha sık ve riskli kullanımla\ndevam eden bir süreçtir.\n◊ Bağımlılıkta tedavi uzun süreli hatta yaşam boyudur, yüksek maliyetlidir ve\ntedavinin başarısı öngörülebilir değildir. Bu yüzden birincil önleme yani insanların\nmadde kullanmaması asıl hedefimizdir.\n◊ İkinci hedef kullanan bireylerin bağımlı olmasını önlemektir. Bu da ikincil\nönleme yani bağımlılık yapıcı maddeyi deneyenlere müdahaleyi kapsar. Deneme\naşamasında olan ergenler ya da yetişkinler psikiyatriye değil birinci basamak\nsağlık hizmetlerine başvurduklarından gerekli müdahale buralarda yapılmalıdır.\n◊ Vücuda alındığında merkezi sinir sistemini etkileyerek fiziksel, ruhsal ve\ndavranışsal değişikliklere sebep olan, bitkisel kimyasal işlemler sonucu oluşturulan\nsentetiklerden elde edilen, sakinleştirici ve/veya uyarıcı etkileri bulunan, kullanma\nisteği durdurulamayan ve kullanılmadığında yoksunluk belirtileri ortaya çıkan tüm\nmaddeler uyuşturucudur.\n◊ Bağımlılık, kronik seyirli bir hastalık olması, bağımlılığa bağlı ortaya çıkan sağlık\nsorunları, bulaşıcı hastalıklara ilişkin risklerin artması, tedavi ve rehabilitasyon\nmaliyetleri, iş gücü kayıpları, uyuşturucu kullanımı olan bireylerde suç işleme, suça\nkarışma, şiddet gibi adli olaylar, aile içi sorunların, ekonomik sorunların artmasvı\nsebebiyle önemli bir toplumsal sorundur.\n◊ Genel Nüfusta Tütün Alkol ve Madde Kullanımına Yönelik Tutum ve Davranış\nAraştırması” verilerine göre 2011 yılında hayatında en az bir kere uyuşturucu madde\nkullananların oranı yüzde 2,7 iken 2018 yılı sonuçlarına göre bu oranın yüzde 3,1’dir.\nTablo 292. MKB tanı kriterleri, DSM 5 (DSM-5, Amerikan Psikiyatri Birliği, Hekimler\nYayın Birliği, 2013’den alınarak düzenlenmiştir).\nAşağıdakilerden en az ikisinin 12 aylık bir süre içinde ortaya çıkmasıyla kendini\ngösteren, klinik olarak önemli bozulmaya yol açan madde kullanımı.\n1. Amaçlanandan daha fazla miktarlarda veya daha uzun süre madde kullanımı\n2 Madde kullanımını azaltmak veya bırakmak istemek ama bunu başaramamak\n3 Maddeye ulaşmak, alkol kullanmak ya da oluşturduğu etkilerden kurtulmak için\nzaman harcaması\n4. Madde kullanmak için güçlü bir dürtü veya istek duymak\n5. İş, ev ya da okulda konumunun gereği olan sorumluluklarını yerine getirememe\nile sonuçlanan madde kullanımı olması\n6. Sosyal yaşamda ya da diğer insanlarla ilişkilerde kalıcı ve tekrarlayıcı sorunlara\nyol açtığı ya da bu sorunları ağırlaştırdığı halde madde kullanımına devam etme\n7. Önemli sosyal, mesleki etkinlikler ve ilgi alanlarına ilişkin etkinliklerin azaltılması\nya da bırakılması\n8. Fiziksel olarak tehlikeli olabilecek durumlarda yineleyici bir şekilde madde\nkullanımının olması\n\nBÖLÜM:SEMPTOMLARA\nKORUYUCU SAĞLIK\nVE ÖZEL DURUMLARA\n1.3.BÖLÜM:\nVE BULGULARA\nYAKLAŞIM YAKLAŞIM\n\n9. Fizyolojik ve psikolojik olarak sıkıntı yaşamasına rağmen kullanmaya devam\netmek\n10. İstenen etkiyi elde etmek için daha fazla madde kullanımı veya aynı ölçüde\nmadde kullanımına karşı daha az etki sağlanması (tolerans)\n11. Kesilme (yoksunluk) belirtileri\nYukarıdaki tanı ölçütlerinden 2 ve üzeri=MKB\nŞiddeti: Hafif: 2-3 semptom, Orta: 4-5 semptom, Şiddetli: ≥6 semptom\n\nDEĞERLENDİRME VE TARAMA\n\n◊ Madde etkisi altında olan hasta ile görüşme yapmayın, ayık olacağı başka\nbir zamana randevu verin. Kendisi ve ailesini başvurabileceği yerler konusunda\nbilgilendirin.\n◊ Madde kullanıp kullanmadığı sorulduğunda EVET yanıtı veren herkese\nkonuştuklarınızın gizli kalacağını vurgulayarak BAPİRT (Bağımlılık Profil İndeksi Risk\nTarama Formu) Madde Ölçeği ile risk taraması yapılmalıdır (Tablo 293)\n◊ BAPİRT Madde taramasını uygularken birden çok madde kullanıyorsa en çok\nkullandığı maddeyi öğrenin. Tüm madde kullanımını toplama yazın.\nTablo 293. BAPİRT Madde Tarama Ölçeği (Kültegin Ögel’in izni ile, Ögel K ve ark.,\nSAMBART Rehberi, Yeniden Yayınları, 2015’den alınmıştır).\nM1 Son bir yıl içinde ne sıklıkta [madde]\nkullandınız?\nM2 [Maddeyi] kestiğinizde veya azalttığınızda\nbazı sorunlar ortaya çıktı mı?\nM3 [Madde] kullandığınız için hayatınızdaki\nbaşka etkinliklerden vazgeçtiğiniz oldu mu?\nM4 [Madde] kullanmak beden veya ruh\nsağlığınızı olumsuz yönde etkiledi mi?\nM5 [Madde] kullanmanız, az sonra sayacağım\nyaşam alanlarından birisi üstünde olumsuz\netkileri oldu mu? Aile ilişkilerinizde?\nArkadaşlarınızla olan ilişkilerinizde? Eğitim\nhayatınızda? İş hayatınızda?\n\nHiçbir zaman\n\nEn az bir kez\n\nÜçten fazla kez\n\nHiçbir zaman\n\nBazen\n\nÇok sık\n\nHiçbir zaman\n\nBazen\n\nÇok sık\n\nHiçbir zaman\n\nBazen\n\nÇok sık\n\nHiçbir zaman\n\nBazen\n\nÇok sık\n\nMadde Kullanım Bozukluğuna Yaklaşım\n\nM6 Gündüz saatlerinde de [madde] kullandığınız Hiçbir zaman\noldu mu?\nBazen\nM7 Hayatınız boyunca hiç damar yoluyla bir\nmadde kullandığınız oldu mu?\n\nÇok sık\n\nHiçbir zaman\n\nBazen\n\nÇok sık\n\nDeğerlendirme: M1-6 puanlarını toplayın.\n4 ve = yüksek riskli\nmadde kullanımı. Damar yolu ile madde kullanımı varsa ölçeği uygulamadan\nyüksek risk kabul edin.\n\nİntoksikasyon\n◊ Madde alımı ya da kısa bir süre sonrasında gelişen ve başka bir nedene bağlı\nolmayan; paranoid hezeyanlar ya da psikotik bir tablo, anksiyete, taşikardi, bulantı,\nepileptik nöbetler, aritmi, serebrovasküler olaylar gibi belirtilerle ortaya çıkan\nintoksikasyon durumunda hasta acil servise sevk edilmelidir.\nMadde Yoksunluğu\n◊ Hastanın yoksunluk belirtileri yaşayıp yaşamadığını değerlendirilmelidir (Tablo\n294).\n◊ Madde kullanıcıları azaltıp, bıraktıkları zaman bazı septomlar ortaya çıkabilir.\nUygulanacak semptoma yönelik tedavi ile hasta biraz rahatlar. Bu sayede hasta\nkontrole gelebilir ve bizimle bağlantısı devam eder. Gerektiğinde sevk etmek için\nde fırsatımız olur.\n◊ Sık görülen uyku sorunları için antihistaminik veya antidepresanlar kullanılabilir\n(mirtazapin, mianserin, trazadon) kullanılabilir.\n◊ Madde kullanan bireyde fiziksel ağrılar, kas spazmları, bulantı ve kusma gibi\nbelirtiler gözlenebilir, bunlara yönelik semptomatik tedavi verilmelidir.\n◊ MKB’a eşlik ruhsal eden ve fiziksel semptomlar araştırılmalı ve gerekirse\nsemptomatik tedavi verilmelidir. Eşlik eden ruhsal sorun aynı anda tedavi\nedilmelidir. Depresyon ve anksiyete hafif düzeyde ise gerekli tedaviler verilmelidir.\n◊ MKB’da gerekli tetkikler yapılmalı ve değerlendirilmelidir.\n\nBÖLÜM:SEMPTOMLARA\nKORUYUCU SAĞLIK\nVE ÖZEL DURUMLARA\n1.3.BÖLÜM:\nVE BULGULARA\nYAKLAŞIM YAKLAŞIM\n\nTablo 294. Maddelerin Yoksunluk Belirtileri\nEsrar ve sentetik kannaboidlerV\n\nOpioidler\n\nBenzodiazepinler\n\nÜşüme,titreme,terleme\nBaş ağrısı,miyalji,somatik ağrılar\nHuzursuzluk, sinirlilik\nÇarpıntı, hipertansiyon\nUykusuzluk\nDürtüsellik\nHafıza bozukluğu\nAnksiyete, irritabilite, ajitasyon\nPsikoz (halüsinasyon ve sanrılar)\nEpileptik nöbetler\n\nTerleme\nBurun akıntısı\nİshal\nUykusuzluk\nSinirlilik\nHuzursuzluk\nAğrı ve kramplar\nŞiddetli madde isteği\nMidriyazis\n\nTerleme, titreme\nKaslarda ağrı, kasılma\nBaş dönmesi, sersemlik\nDiplopi, bulanık görme\nTinnitus, baş ağrısı\nBulantı, kusma, ishal\nParestezi, grip belirtileri\nUykusuzluk,anksiyete,depresyon\nAlgı bozuklukları\nİrritabilite,huzursuzluk,ajitasyon\n\nUyarıcı Maddeler (kokain, ekstazi,\namfetamin, metamfetamin)\n\nİnhalanlar\n\nHalüsinojenler\n\nYoğun aşerme, ajitasyon, irritabilite\nDepresyon, anksiyete\nHayattan keyif alamama\nDurgunluk, yorgunluk\nUyku ve iştah artışı\nKas ağrıları, intihar fikirleri\n\nTerleme,taşikardi\nbulantı,kusma\nUykusuzluk,\nhuzursuzluk, Dikkat,\nkonsantrasyonda\nbozulma, İştah kaybı\nBurun akıntısı, sulu\ngözler, ,\nDepresyon,\nanksiyete\n\nYorgunluk, sinirlilik\nAnhedoni\nAşerme\nDepresif belirtiler\n\nTEDAVİ\n\n◊ Birinci basamak sağlık hizmetlerinde verilen kısa danışmanlığın (5-10 dakika),\nMKB ‘da tedaviye yönlendirmede etkili olduğu bilinmektedir.\n◊ Değişim döngüsü modelinde (Prochaska ve Di Clemente) kişinin hangi evrede\nolduğunu bilerek müdahale yapmak gerekmektedir. Farkındalık öncesinde olan\nbir kişiden maddeyi bırakmasını istemek işe yaramayacaktır. Onun farkındalık\nevresine geçişini sağlamak önemlidir. Farkına varma evresinde ise, kişinin\nmaddeyi bırakmasını istemek yerine madde kullanımını bırakma kararını vermesini\nsağlamaya çalışmalıdır.\n◊ Madde kullananlar bırakmak istemeyebilir, bırakma düşüncesi anksiyete\nyarattığından denemek istemezler ya da istedikleri zaman bırakabileceklerine\ninanırlar. Bu nedenle kişi kesmeyi reddediyorsa, bazen bırakmak yerine kullandığı\nmaddenin miktarını veya kullanım sıklığını azaltmak önerilebilir. Kişi kullandığı\nmaddenin miktarını veya kullanım sıklığını azaltamadığını gördüğünde, bırakmanın\ngerekliliği konusunda daha kolay ikna olur.\n\nMadde Kullanım Bozukluğuna Yaklaşım\n\nTablo 295. Değişim Evreleri\nEvreler\n\nÖzellikleri\n\nHasta söylemleri\n\nFarkındalık Öncesi\n\nAMK olumsuz etkileri farkında\ndeğildirler. Zararı olduğuna\ninanmazlar. Değişime hazır\ndeğildirler.\n\n‘AMK benim için sorun\nyaratmıyor’\n‘Bırakmak/azaltmak\nistemiyorum’\n\nFarkındalık\n\nAMK zararlarının/kendini\nolumsuz etkilediğinin\nfarkındadır. Ama bırakmayı\ndüşünmezler.\n\n‘AMK benim için\nsorun ama bırakmayı\ndüşünmüyorum’\n\nHazırlık\n\nBırakmaya karar vermiş ama\nhenüz eyleme geçmemiştir.\n\n‘Bırakacağım’\n\nEylem\n\nAlkol/maddeyi bırakmıştır.\nTekrar başlama riski yüksektir.\n\n‘Bıraktım’\n\nSürdürme\n\nBırakmayı sürdürme\nçabasındadır.\n\n‘Bir aydır içmiyorum’\n\nYeniden Başlama\n\nTekrar AMK’a başlamıştır.\n\n‘Tekrar içmeye başladım’\n\n◊ Adsız Narkolikler (AN), 12 basamak yaklaşımı uygulayan kendi kendine yardım\ngruplarıdır. Bu sayede madde bağımlılarına duygusal destek sunan bir uluslararası\nkuruluştur. Adsız narkotiklere devam eden bireylerin ayık kalma sürelerinin daha\nuzun olduğu gösterilmiştir. AN’nin etkililiği katılımcılara sağladığı sosyalleşme\nimkânı ve ayık kalma motivasyonu bireye maddeden uzak kalma konusunda\nyardımcı olmaktadır.\n◊ AMATEM, alkol ve madde kullanım bozukluğu konusunda tedavi ve eğitim\namacıyla kurulmuş olup, AMATEM bünyesinde gerçekleştirilen müdahale yöntemi\nüç bölümden oluşur; “Detoksifikasyon (arındırma), ilaçla müdahale ve psikososyal (ilaçsız) müdahale.\n◊ Detoksifikasyon aşamasında madde bağımlısının maddeye olan arzusundan\nkaynaklanan yoksunluk belirtilerinin azaltılması amacıyla uygulanacak olan\nmüdahaleler gerçekleştirilmektedir. Bu aşama 7 ila 10 gün arasında bir zamanda\ntamamlanmaktadır.\n◊ Farmakolojik müdahale aşmasında ise detoksifikasyon süreci sona erince\nbağımlılık tedavisinde kullanılan ilaçların başlanması ile iyileşme süreci devam\netmektedir.\n◊ Son aşama olan psiko-sosyal müdahale sürecinde ise bağımlının alkol veya\nmaddeye tekrardan yönelmemesi için gerekli olan psiko-sosyal faaliyetler\ngerçekleştirilmektedir. Psikoterapiler ve benzeri grup çalışmaları ile yaklaşık olarak\n14 gün ile 28 gün arasındaki bir zaman diliminde süreç tamamlanmaktadır.\n\nBÖLÜM:SEMPTOMLARA\nKORUYUCU SAĞLIK\nVE ÖZEL DURUMLARA\n1.3.BÖLÜM:\nVE BULGULARA\nYAKLAŞIM YAKLAŞIM\n\n‘Benim içmem bir\nazaltmak istemiyorum.’\n\nEYLEM\nHAZIRLIK\n\nFARKINDALIK\n\nAncak bu evrede tekrar\n\nSÜRDÜRME\n\nistemektedir. Ancak\nsürdürmektedir.\nolumsuz etkilerin\n\nFARKINDALIK\n‘Benim içmem bir sorun\n\nMaddenin kendisini\nolumsuz yönde\nAncak henüz madde\n\n‘Tekrar içmeye\n\nDÖNGÜSÜ\n\nTekrar madde\n\nŞekil 205. Değişim Döngüsü\n◊ Ergenlerde risk taraması ergenler için hazırlanmış Madde Anketi kullanılmalıdır\n(Tablo 296).\n◊ Ergenin madde kullanımı yanında ruhsal sorunu olup olmadığı, yoksunluk\nbelirtileri yaşayıp yaşamadığı ve hangi maddeleri kullanıp kullanmadığı öğrenilir.\nEğer eşlik eden ruhsal sorunlar, yoksunluk belirtileri ve birden fazla madde kullanımı\nvarsa, psikiyatriye sevk edilmelidir.\n◊ Aileyle muhakkak görüşülmeli ve aile bilgilendirilmelidir.\n◊ Yüksek riskli kullanımı olan gençler ise bağımlılık merkezlerine yönlendirilmelidir.\nEğer gitmek istemezse değişim motivasyonunu artırmak için görüşme yapılmalı\nve tekrar etkin tavsiyede bulunulmalıdır (Şekil 206. Ergenlerde Alkol/Madde\nKullanımına Yaklaşım Akış Şeması).\nTablo 296. Ergen Madde Risk Tarama Ölçeği (Kültegin Ögel’in izni ile, Ögel K ve\nark., SAMBART Rehberi, Yeniden Yayınları, 2015’den alınmıştır).\nGM1 Son bir yıl içinde ne sıklıkta [madde] kullandın? Hiç\n\nSadece bir iki kez\n\nAyda 1-3 kere\n\nHaftada 1-5 kez\n\nHemen hemen her gün 4\n2 puan ve üstü YÜKSEK RİSKLİ kullanıma işaret etmektedir.\n\nMadde Kullanım Bozukluğuna Yaklaşım\n\nŞekil 206. Ergenlerde Alkol/Madde Kullanımına Yaklaşım Akış Şeması\n\nGüncel Kılavuzlar ve Ek Kaynaklar\n1. SAMBART – Birinci Basamakta Alkol ve Madde Kullanımına Yönelik Kısa Müdahale\nRehberi (Ögel K. ve ark.) https://www.yeniyayinlari.com.tr/sigara-alkol-ve-maddebagimliligi-rehberlik-ve-tarama-programi-sambart [cited 2025 Dec 26].\n2. Alkol ve Madde Kullanım Bozuklukları Tedavi ve İzlem Klinik Protokolü – T.C. Sağlık\nBakanlığı (2022) https://shgm.saglik.gov.tr/TR-98392/alkol-ve-madde-kullanimbozukluklari-tedavi-ve-izlem-klinik-protokolu.html [cited 2025 Dec 26].\n3. WHO – The ASSIST-linked brief intervention for hazardous and harmful\nsubstance use (Primary Care Manual) https://www.who.int/publications/i/item/\nWHO-MSD-MER-10.1 [cited 2025 Dec 26].\n\nKaynakça\n\n1. Amerikan Psikiyatri Birliği. (2013). Ruhsal bozuklukların tanısal ve sayımsal el\nkitabı (5. Bs.) içinde (s. 237-239). (Çev. Köroğlu, E.). Ankara: Hekimler Yayın Birliği.\n2. Bağımlılık Tanı ve Tedavi Temel Kitabı N. Dilbaz, I. Göğceğiz, C. O. Noyan, Ö. Kazan\nKızılkurt (eds). Ankara Nobel Tıp Kitabevleri, 237-260. 2022. ISBN; 978-625-7146-77-7\n\nBÖLÜM:SEMPTOMLARA\nKORUYUCU SAĞLIK\nVE ÖZEL DURUMLARA\n1.3.BÖLÜM:\nVE BULGULARA\nYAKLAŞIM YAKLAŞIM\n\n4. Acar, T. (2024). Madde Kullanımı Açısından Koruyucu Hekimlik. Turkiye Klinikleri\nFamily Medicine-Special Topics, 15(2), 83-87\n5. US Preventive Services Task Force. Screening for unhealthy drug use:\nUS Preventive Services Task Force recommendation statement. JAMA.\n2020;323(22):2301–2309.\n6. Şengezer,Tijen (2020).”Madde Kullanım Bozuklukları için Davranışsal Terapiler”.\nEsra Saatçi (Ed.)Rakel Aile Hekimliği Dokuzuncu Baskı(pp.1152-1163).Ankara:Güneş\nTıp Kitabevleri\n7. Kahan M. Management of substance use disorders in primary care. Toronto:\nWomen's College Hospital; 2015.\n8. Kılıç M, Önal S. Birinci basamak sağlık hizmetlerinde alkol-madde kullanımı olan\nbireylere yaklaşım. Turkish Journal of Family Practice. 2023;14(3):390–6. doi:10.15511/\ntjtfp.23.00390.\n9. Şengezer Tijen, Hasan Kaya (2020).”Aile Hekimliğinde Alkol ve Madde Kullanım\nBozuklukları”Aydın Çiftçi(Ed).Birinci Basamakta ve Aile Hekimliğinde Güncel Tanı ve\nTedavi (pp.103-110).Ankara: Nobel Tıp Kitabevleri.\n10. Hooker SA, Punjabi A, Justesen K, Boyle L, Sherman MD. Encouraging health\nbehavior change: eight evidence-based strategies. Fam Pract Manag. 2018\nMar-Apr;25(2):31–36","word_count":1816}